av_mcp_client/__init__.py
av_mcp_client/llm_manger.py
av_mcp_client/mcp_client.py
av_mcp_client-0.3.3.dist-info/METADATA
av_mcp_client-0.3.3.dist-info/WHEEL
av_mcp_client-0.3.3.dist-info/top_level.txt
av_mcp_client-0.3.3.dist-info/RECORD
