Metadata-Version: 2.4
Name: av_mcp_client
Version: 0.3.3
Summary: Add your description here
Requires-Python: >=3.11
Requires-Dist: google-genai>=1.26.0
Requires-Dist: langchain>=0.3.26
Requires-Dist: langchain-google-genai>=2.1.8
Requires-Dist: langchain-mcp-adapters>=0.1.9
Requires-Dist: langchain-openai>=0.3.28
Requires-Dist: langgraph>=0.5.4
Requires-Dist: openai>=1.97.1
Requires-Dist: tiktoken>=0.9.0
Requires-Dist: twine>=6.1.0
